cvxcla/__init__.py
cvxcla/cla.py
cvxcla/first.py
cvxcla/optimize.py
cvxcla/types.py
cvxcla-1.5.1.dist-info/METADATA
cvxcla-1.5.1.dist-info/WHEEL
cvxcla-1.5.1.dist-info/licenses/LICENSE
cvxcla-1.5.1.dist-info/RECORD
