Metadata-Version: 2.4
Name: cvxcla
Version: 1.5.1
Summary: Critical line algorithm for the efficient frontier
Project-URL: repository, https://github.com/cvxgrp/cvxcla
Author-email: Thomas Schmelzer <thomas.schmelzer@gmail.com>, Philipp Schiele <pschiele@stanford.edu>
License-File: LICENSE
Requires-Python: >=3.11
Requires-Dist: kaleido==1.2.0
Requires-Dist: numpy>=2.0.0
Requires-Dist: plotly>=6.0.1
